spark_privacy_preserver/__init__.py
spark_privacy_preserver/clustering_anonymizer.py
spark_privacy_preserver/clustering_preserver.py
spark_privacy_preserver/differential_privacy.py
spark_privacy_preserver/gv.py
spark_privacy_preserver/mondrian_preserver.py
spark_privacy_preserver/clustering_utils/__init__.py
spark_privacy_preserver/clustering_utils/cluster_init.py
spark_privacy_preserver/clustering_utils/clustering.py
spark_privacy_preserver/clustering_utils/data_loss.py
spark_privacy_preserver/clustering_utils/distance_calculation.py
spark_privacy_preserver/clustering_utils/input_validate.py
spark_privacy_preserver/clustering_utils/kmodes.py
spark_privacy_preserver/mondrian_utils/__init__.py
spark_privacy_preserver/mondrian_utils/utility.py
spark_privacy_preserver-0.3.1.dist-info/LICENSE
spark_privacy_preserver-0.3.1.dist-info/METADATA
spark_privacy_preserver-0.3.1.dist-info/WHEEL
spark_privacy_preserver-0.3.1.dist-info/top_level.txt
spark_privacy_preserver-0.3.1.dist-info/RECORD
