Metadata-Version: 2.1
Name: spark-privacy-preserver
Version: 0.3.1
Summary: Anonymizing Library for Apache Spark
Home-page: https://github.com/ThaminduR/spark-privacy-preserver
Author: thamindu
Author-email: thamindu.randil@gmail.com
License: UNKNOWN
Platform: UNKNOWN
Classifier: Programming Language :: Python :: 3
Classifier: License :: OSI Approved :: Apache Software License
Classifier: Operating System :: OS Independent
Requires-Python: >=3.6
Requires-Dist: pandas (>=1.1)
Requires-Dist: pyspark (==2.4.5)
Requires-Dist: pyarrow (==0.17.1)
Requires-Dist: diffprivlib (==0.2.1)
Requires-Dist: tabulate (==0.8.7)
Requires-Dist: mypy (>=0.770)
Requires-Dist: kmodes
